unilogger/HDFlogger.py
unilogger/__init__.py
unilogger/asyncio_helper.py
unilogger/csvlogger.py
unilogger/schedule.py
unilogger/bus/__init__.py
unilogger/bus/addupi.py
unilogger/bus/base.py
unilogger/bus/modbus.py
unilogger/bus/sdi12.py
unilogger-2022.11.14.dist-info/LICENSE
unilogger-2022.11.14.dist-info/METADATA
unilogger-2022.11.14.dist-info/WHEEL
unilogger-2022.11.14.dist-info/top_level.txt
unilogger-2022.11.14.dist-info/RECORD
