Metadata-Version: 2.1
Name: unilogger
Version: 2022.11.14
Summary: A flexible interface for various sensor bus systems
Author-email: Philipp Kraft <philipp.kraft@envr.jlug.de>
License: MIT License
Project-URL: Homepage, https://github.com/jlu-ilr-hydro/unilogger
Project-URL: Bug Tracker, https://github.com/jlu-ilr-hydro/unilogger/issues
Classifier: Programming Language :: Python :: 3
Classifier: License :: OSI Approved :: MIT License
Classifier: Operating System :: OS Independent
Requires-Python: >=3.9
License-File: LICENSE
Requires-Dist: umodbus
Requires-Dist: aiohttp
Requires-Dist: BeautifulSoup4
Requires-Dist: aioserial
Requires-Dist: pyyaml
Requires-Dist: lxml
Requires-Dist: pyserial
Requires-Dist: asteval
Requires-Dist: pandas
Requires-Dist: tables
Requires-Dist: openpyxl
